guolei_py3_components
