Metadata-Version: 2.1
Name: guolei-py3-components
Version: 1.1.1
Summary: a python3 components by guolei
Home-page: https://github.com/guolei19850528/guolei_py3_components
Author: guolei
Author-email: 174000902@qq.com
License: MIT
Platform: UNKNOWN
Requires-Python: >=3.0
